thaiaddressclean/__init__.py
thaiaddressclean/cleans/clean_address_thailand.py
thaiaddressclean/refs/thai_addr.csv
thaiaddressclean-0.0.3.dist-info/METADATA
thaiaddressclean-0.0.3.dist-info/WHEEL
thaiaddressclean-0.0.3.dist-info/licenses/LICENSE
thaiaddressclean-0.0.3.dist-info/RECORD
