Metadata-Version: 2.3
Name: thaiaddressclean
Version: 0.0.3
Summary: thaiaddressclean
Author-email: dData <user@data.co.th>
License-File: LICENSE
Classifier: License :: OSI Approved :: MIT License
Classifier: Operating System :: OS Independent
Classifier: Programming Language :: Python :: 3
Requires-Python: >=3.10
Requires-Dist: pandas
